hyperui/.DS_Store
hyperui/__init__.py
hyperui/libboost_python.dylib
hyperui/pyhyperui.so
hyperui/HyperCore.framework/HyperCore
hyperui/HyperCore.framework/Headers/HyperCore.h
hyperui/HyperCore.framework/Headers/config.h
hyperui/HyperCore.framework/Headers/platformConfig.h
hyperui/HyperCore.framework/Headers/Basic/Base64Coder.h
hyperui/HyperCore.framework/Headers/Basic/BaseUtils.h
hyperui/HyperCore.framework/Headers/Basic/BaseValue.h
hyperui/HyperCore.framework/Headers/Basic/BinaryData.h
hyperui/HyperCore.framework/Headers/Basic/DataTypes.h
hyperui/HyperCore.framework/Headers/Basic/EdgeId.h
hyperui/HyperCore.framework/Headers/Basic/Enums.h
hyperui/HyperCore.framework/Headers/Basic/Environment.h
hyperui/HyperCore.framework/Headers/Basic/GeometryUtils.h
hyperui/HyperCore.framework/Headers/Basic/IBaseObject.h
hyperui/HyperCore.framework/Headers/Basic/Logger.h
hyperui/HyperCore.framework/Headers/Basic/Mutex.h
hyperui/HyperCore.framework/Headers/Basic/PackedFile.h
hyperui/HyperCore.framework/Headers/Basic/RecursiveSharedLock.h
hyperui/HyperCore.framework/Headers/Basic/StringUtils.h
hyperui/HyperCore.framework/Headers/Basic/TokenizeUtils.h
hyperui/HyperCore.framework/Headers/Curves/Curves.h
hyperui/HyperCore.framework/Headers/Curves/SCubicCurve.h
hyperui/HyperCore.framework/Headers/DataStructs/DataStructs.h
hyperui/HyperCore.framework/Headers/DataStructs/SBBox2D.h
hyperui/HyperCore.framework/Headers/DataStructs/SBBox3D.h
hyperui/HyperCore.framework/Headers/DataStructs/SCircle.h
hyperui/HyperCore.framework/Headers/DataStructs/SColor.h
hyperui/HyperCore.framework/Headers/DataStructs/SCone2D.h
hyperui/HyperCore.framework/Headers/DataStructs/SDate.h
hyperui/HyperCore.framework/Headers/DataStructs/SGradient.h
hyperui/HyperCore.framework/Headers/DataStructs/SGradientStop.h
hyperui/HyperCore.framework/Headers/DataStructs/SIndexedColor.h
hyperui/HyperCore.framework/Headers/DataStructs/SIntVector2D.h
hyperui/HyperCore.framework/Headers/DataStructs/SMatrix2D.h
hyperui-1.0.1.dist-info/LICENSE
hyperui-1.0.1.dist-info/METADATA
hyperui-1.0.1.dist-info/WHEEL
hyperui-1.0.1.dist-info/top_level.txt
hyperui-1.0.1.dist-info/RECORD
