Metadata-Version: 2.1
Name: hyperui
Version: 1.0.1
Summary: A cross-platform application and UI framework
Home-page: https://github.com/sadcatsoft/hyperui
Author: Sad Cat Software
Author-email: sadcatsoft@gmail.com
License: MIT License
Keywords: ui framework opengl app
Platform: UNKNOWN
Classifier: Programming Language :: Python :: 2.7
Classifier: License :: OSI Approved :: MIT License
Classifier: Operating System :: OS Independent
Classifier: Topic :: Software Development :: Libraries :: Application Frameworks
Requires-Python: >=2.7
